dj_termsearch-0.2.0.dist-info/metadata.json
dj_termsearch-0.2.0.dist-info/DESCRIPTION.rst
dj_termsearch-0.2.0.dist-info/RECORD
dj_termsearch-0.2.0.dist-info/METADATA
dj_termsearch-0.2.0.dist-info/top_level.txt
dj_termsearch-0.2.0.dist-info/WHEEL
termsearch/__init__.py
termsearch/views.py
