Metadata-Version: 2.0
Name: dj-termsearch
Version: 0.2.0
Summary: Simple term searches for Django CBV's.
Home-page: https://github.com/Ogreman/django-termsearch
Author: James Cox
Author-email: james.aaron.cox@gmail.com
License: BSD
Keywords: django,terms,search
Platform: UNKNOWN
Classifier: Development Status :: 2 - Pre-Alpha
Classifier: Framework :: Django
Classifier: Intended Audience :: Developers
Classifier: License :: OSI Approved :: BSD License
Classifier: Natural Language :: English
Classifier: Programming Language :: Python :: 2
Classifier: Programming Language :: Python :: 2.6
Classifier: Programming Language :: Python :: 2.7
Classifier: Programming Language :: Python :: 3
Classifier: Programming Language :: Python :: 3.3
